appengine_clean/__init__.py
appengine_clean/appengine_clean.py
appengine_clean-0.1.6.dist-info/LICENSE
appengine_clean-0.1.6.dist-info/METADATA
appengine_clean-0.1.6.dist-info/WHEEL
appengine_clean-0.1.6.dist-info/entry_points.txt
appengine_clean-0.1.6.dist-info/top_level.txt
appengine_clean-0.1.6.dist-info/RECORD
