Metadata-Version: 2.1
Name: appengine-clean
Version: 0.1.6
Summary: Clean old AppEngine versions
Home-page: https://github.com/poweredbygrow/appengine_clean
Author: David Grant
Author-email: davidgrant@gmail.com
License: UNKNOWN
Keywords: utility,miscellaneous,library
Platform: UNKNOWN
Classifier: Programming Language :: Python :: 3.7
